lose/__init__.py
lose/dataHandler.py
lose/test/__init__.py
lose/test/__main__.py
lose/test/unittests.py
lose-1.0.0.dist-info/LICENSE
lose-1.0.0.dist-info/METADATA
lose-1.0.0.dist-info/WHEEL
lose-1.0.0.dist-info/top_level.txt
lose-1.0.0.dist-info/RECORD
